web.dispatch.route-1.0.0-py3.5-nspkg.pth
web/dispatch/route/__init__.py
web/dispatch/route/dispatch.py
web/dispatch/route/helper.py
web/dispatch/route/release.py
web/dispatch/route/router.py
web.dispatch.route-1.0.0.dist-info/DESCRIPTION.rst
web.dispatch.route-1.0.0.dist-info/entry_points.txt
web.dispatch.route-1.0.0.dist-info/METADATA
web.dispatch.route-1.0.0.dist-info/metadata.json
web.dispatch.route-1.0.0.dist-info/namespace_packages.txt
web.dispatch.route-1.0.0.dist-info/RECORD
web.dispatch.route-1.0.0.dist-info/top_level.txt
web.dispatch.route-1.0.0.dist-info/WHEEL
web.dispatch.route-1.0.0.dist-info/zip-safe
