Metadata-Version: 2.0
Name: web.dispatch.route
Version: 1.0.0
Summary: Route-based dispatch; highly optimized tree-based routes for WebCore, with support for regular expression components.
Home-page: https://github.com/marrow/web.dispatch.route
Author: Alice Bevan-McGregor
Author-email: alice@gothcandy.com
License: MIT
Platform: UNKNOWN
Classifier: Development Status :: 5 - Production/Stable
Classifier: Environment :: Console
Classifier: Environment :: Web Environment
Classifier: Intended Audience :: Developers
Classifier: License :: OSI Approved :: MIT License
Classifier: Operating System :: OS Independent
Classifier: Programming Language :: Python
Classifier: Programming Language :: Python :: 2
Classifier: Programming Language :: Python :: 2.7
Classifier: Programming Language :: Python :: 3
Classifier: Programming Language :: Python :: 3.3
Classifier: Programming Language :: Python :: 3.4
Classifier: Programming Language :: Python :: 3.5
Classifier: Programming Language :: Python :: Implementation :: CPython
Classifier: Programming Language :: Python :: Implementation :: PyPy
Classifier: Topic :: Internet :: WWW/HTTP :: WSGI
Classifier: Topic :: Software Development :: Libraries :: Python Modules
Provides-Extra: development
Requires-Dist: pytest; extra == 'development'
Requires-Dist: pytest-cov; extra == 'development'
Requires-Dist: pytest-flakes; extra == 'development'
Requires-Dist: pytest-cagoule; extra == 'development'
Requires-Dist: pytest-spec; extra == 'development'
